mysql_inter_wrapper/__init__.py
mysql_inter_wrapper/mysql_inter_wrapper.py
mysql_inter_wrapper-1.0.1.dist-info/licenses/LICENSE
mysql_inter_wrapper-1.0.1.dist-info/METADATA
mysql_inter_wrapper-1.0.1.dist-info/WHEEL
mysql_inter_wrapper-1.0.1.dist-info/top_level.txt
mysql_inter_wrapper-1.0.1.dist-info/RECORD
