Metadata-Version: 2.4
Name: mysql-inter-wrapper
Version: 1.0.1
Summary: A lightweight Python wrapper for MySQL CRUD operations with Pandas support.
Author: Wilfred Kisitu
Author-email: wkfinancials@gmail.com
Classifier: Programming Language :: Python :: 3
Classifier: License :: OSI Approved :: MIT License
Classifier: Operating System :: OS Independent
Requires-Python: >=3.7
License-File: LICENSE
Requires-Dist: mysql-connector-python
Requires-Dist: pandas
Dynamic: author
Dynamic: author-email
Dynamic: classifier
Dynamic: license-file
Dynamic: requires-dist
Dynamic: requires-python
Dynamic: summary
